lib/__init__.py
lib/data_handling.py
lib/get_myplaylist_api.py
lib/model.py
sc3mylibrary-1.0.0.dist-info/LICENSE
sc3mylibrary-1.0.0.dist-info/METADATA
sc3mylibrary-1.0.0.dist-info/WHEEL
sc3mylibrary-1.0.0.dist-info/top_level.txt
sc3mylibrary-1.0.0.dist-info/RECORD
